ipa2/__init__.py
ipa2/main.py
ipa2/test.py
ipa2/data/ady.tsv
ipa2/data/afr.tsv
ipa2/data/amh.tsv
ipa2/data/ang.tsv
ipa2/data/ara.tsv
ipa2/data/arg.tsv
ipa2/data/arm-e.tsv
ipa2/data/arm-w.tsv
ipa2/data/aze.tsv
ipa2/data/bak.tsv
ipa2/data/bel.tsv
ipa2/data/bos.tsv
ipa2/data/bul.tsv
ipa2/data/bur.tsv
ipa2/data/cat.tsv
ipa2/data/cze.tsv
ipa2/data/dan.tsv
ipa2/data/dut.tsv
ipa2/data/egy.tsv
ipa2/data/eng-uk.tsv
ipa2/data/eng-us.tsv
ipa2/data/enm.tsv
ipa2/data/epo.tsv
ipa2/data/est.tsv
ipa2/data/eus.tsv
ipa2/data/fas.tsv
ipa2/data/fin.tsv
ipa2/data/fra-qu.tsv
ipa2/data/fra.tsv
ipa2/data/geo.tsv
ipa2/data/ger.tsv
ipa2/data/gle.tsv
ipa2/data/glg.tsv
ipa2/data/grc.tsv
ipa2/data/gre.tsv
ipa2/data/hbs-cyrl.tsv
ipa2/data/hbs-latn.tsv
ipa2/data/hin.tsv
ipa2/data/hun.tsv
ipa2/data/ice.tsv
ipa2/data/ido.tsv
ipa2/data/ina.tsv
ipa2/data/ind.tsv
ipa2/data/isl.tsv
ipa2/data/ita.tsv
ipa2/data/jpn.tsv
ipa2/data/kaz.tsv
ipa2/data/khm.tsv
ipa2/data/kor.tsv
ipa2/data/kur.tsv
ipa2/data/lat-clas.tsv
ipa2/data/lat-eccl.tsv
ipa2/data/lit.tsv
ipa2/data/ltz.tsv
ipa2/data/mac.tsv
ipa2/data/mlt.tsv
ipa2/data/mri.tsv
ipa2/data/msa.tsv
ipa2/data/nan.tsv
ipa2/data/nob.tsv
ipa2/data/ori.tsv
ipa2/data/pap.tsv
ipa2/data/pol.tsv
ipa2/data/por-bz.tsv
ipa2/data/por-po.tsv
ipa2/data/ron.tsv
ipa2/data/rus.tsv
ipa2/data/san.tsv
ipa2/data/slk.tsv
ipa2/data/slo.tsv
ipa2/data/slv.tsv
ipa2/data/sme.tsv
ipa2/data/snd.tsv
ipa2/data/spa-latin.tsv
ipa2/data/spa-me.tsv
ipa2/data/spa.tsv
ipa2/data/sqi.tsv
ipa2/data/srp.tsv
ipa2/data/swa.tsv
ipa2/data/swe.tsv
ipa2/data/syc.tsv
ipa2/data/tam.tsv
ipa2/data/tat.tsv
ipa2/data/tgl.tsv
ipa2/data/tha.tsv
ipa2/data/tts.tsv
ipa2/data/tuk.tsv
ipa2/data/tur.tsv
ipa2/data/uig.tsv
ipa2/data/ukr.tsv
ipa2/data/urd.tsv
ipa2/data/uzb.tsv
ipa2/data/vie-c.tsv
ipa2/data/vie-n.tsv
ipa2/data/vie-s.tsv
ipa2/data/wel-nw.tsv
ipa2/data/wel-sw.tsv
ipa2/data/yue.tsv
ipa2/data/zho-s.tsv
ipa2/data/zho-t.tsv
ipa2-0.8.0.dist-info/METADATA
ipa2-0.8.0.dist-info/WHEEL
ipa2-0.8.0.dist-info/top_level.txt
ipa2-0.8.0.dist-info/zip-safe
ipa2-0.8.0.dist-info/RECORD
