Metadata-Version: 2.1
Name: ipa2
Version: 0.8.0
Summary: Tools for convert Text to IPA in python
Home-page: https://github.com/voidful/ipa2
Author: voidful
Author-email: voidful.stack@gmail.com
License: UNKNOWN
Keywords: nlp file io string text mining ipa voice
Platform: UNKNOWN
Classifier: Development Status :: 4 - Beta
Classifier: Intended Audience :: Developers
Classifier: Topic :: Software Development :: Build Tools
Classifier: License :: OSI Approved :: MIT License
Classifier: Programming Language :: Python :: 3
Classifier: Programming Language :: Python :: 3.4
Classifier: Programming Language :: Python :: 3.5
Classifier: Programming Language :: Python :: 3.6
Requires-Dist: nlp2
